funcoes_leo/__init__.py
funcoes_leo/funcoes.py
funcoes_leo-0.1.2.dist-info/METADATA
funcoes_leo-0.1.2.dist-info/WHEEL
funcoes_leo-0.1.2.dist-info/RECORD
